pytion/__init__.py
pytion/api.py
pytion/envs.py
pytion/exceptions.py
pytion/models.py
pytion/query.py
tests/__init__.py
tests/conftest.py
tests/fixtures.py
tests/test_api.py
tests/test_models.py
tests/test_query.py
pytion-1.3.5.dist-info/LICENSE
pytion-1.3.5.dist-info/METADATA
pytion-1.3.5.dist-info/WHEEL
pytion-1.3.5.dist-info/top_level.txt
pytion-1.3.5.dist-info/RECORD
