Metadata-Version: 2.1
Name: pytion
Version: 1.3.5
Summary: Unofficial Python client for official Notion API
Home-page: https://github.com/lastorel/pytion
Author: Yegor Gomzin
Author-email: slezycmex@mail.ru
Project-URL: Bug Tracker, https://github.com/lastorel/pytion/issues
Project-URL: Changelog, https://github.com/lastorel/pytion/blob/main/CHANGELOG.md
Classifier: Programming Language :: Python :: 3.7
Classifier: Programming Language :: Python :: 3.8
Classifier: Programming Language :: Python :: 3.9
Classifier: Programming Language :: Python :: 3.10
Classifier: Programming Language :: Python :: 3.11
Classifier: License :: OSI Approved :: GNU General Public License v3 (GPLv3)
Classifier: Operating System :: OS Independent
Requires-Python: >=3.7
License-File: LICENSE
Requires-Dist: requests >=2.26.0
